DartDataReader/__init__.py
DartDataReader/fetcher.py
DartDataReader/reader.py
DartDataReader/utils.py
DartDataReader/data_reader/__init__.py
DartDataReader/data_reader/corp.py
DartDataReader/data_reader/fundamental.py
DartDataReader-1.0.0.dist-info/METADATA
DartDataReader-1.0.0.dist-info/WHEEL
DartDataReader-1.0.0.dist-info/top_level.txt
DartDataReader-1.0.0.dist-info/RECORD
