Metadata-Version: 2.1
Name: DartDataReader
Version: 1.0.0
Summary: 한국 전자공시시스템 OPEN-API 활용을 위한 TOOL
Home-page: https://github.com/jackmappotion/DartDataReader
Author: jackmappotion
Author-email: jackmappotion@gmail.com
Classifier: Programming Language :: Python :: 3
Classifier: License :: OSI Approved :: MIT License
Classifier: Operating System :: OS Independent
Requires-Python: >=3.7
Requires-Dist: requests >=2.0.0
Requires-Dist: pandas >=2.0.0
